{
    "version": "0.0.1",
    "id": "heat5",
    "use_case": "HELCOM HEAT HOLAS",
    "title": {"en": "Reproducing HEAT HOLAS results: Compute Assessment"},
    "description": {
        "en": "Compute the Assessment (i.e. EQRS per assessment unit, grouped by overall and criterial level indicators) using HELCOM's HEAT assessment code, for a selected HOLAS assessment period. The calculation is based on the Assessment Indicators (i.e. EQRS per assessment period per assessment unit) which you have to provide as a CSV file. This tool represents the fifth and last part of the original HEAT assessment computation script."
    },
    "jobControlOptions": ["sync-execute", "async-execute"],
    "keywords": ["HELCOM", "HEAT", "HOLAS"],
    "links": [{
        "type": "text/html",
        "rel": "about",
        "title": "GitHub repo for the original HEAT analysis",
        "href": "https://github.com/ices-tools-prod/HEAT/tree/master",
        "hreflang": "en-US"
    },
    {
        "type": "text/html",
        "rel": "about",
        "title": "GitHub repo for the continued HEAT analysis",
        "href": "https://github.com/AquaINFRA/HEAT/tree/aquabranch",
        "hreflang": "en-US"
    }],
    "inputs": {
        "assessment_period": {
            "title": "Assessment Period",
            "description": "The HOLAS assessment period which is used for the HEAT analysis. It can be HOLAS-2 (2011-2016) or HOLAS-3 (2016-2021) or custom for whole monitoring period (1877-9999). Note that assessment period defines the indicators used and integrations rules, where as the sample data needs to be defined separately. Allowed values: HOLAS-2, HOLAS-3, Other.",
            "schema": {
                "type": "string",
                "enum": [
                  "HOLAS-2",
                  "HOLAS-3",
                  "Other"
                ]
            },
            "minOccurs": 1,
            "maxOccurs": 1,
            "metadata": null,
            "keywords": ["HOLAS"]
        },
        "assessment_indicators": {
            "title": "Assessment Indicators Table",
            "description": "CSV file of calculated EQRS per assessment period per assessment unit (AssessmentIndicators.csv).",
            "schema": {
                "type": "object",
                "contentMediaType": "text/csv"
            },
            "minOccurs": 1,
            "maxOccurs": 1,
            "metadata": null,
            "keywords": []
        }
    },
    "outputs": {
        "assessment": {
            "title": "Assessment Table",
            "description": "CSV file: table of calculated EQRS per assessment unit, grouped by overall and criterial level indicators (Assessment.csv).",
            "schema": {
                "type": "object",
                "contentMediaType": "text/csv"
            }
        }
    },
    "example": {
        "inputs": {
            "assessment_indicators": "http://exampleserver.fi/AssessmentIndicators.csv",
            "assessment_period": "HOLAS-2"
        }
    }
}